utlib/__init__.py
utlib/files_utils.py
utlib/numbers_utils.py
utlib/strings_utils.py
utlib/terminal_utils.py
utlib-0.3.4.dist-info/licenses/LICENSE
utlib-0.3.4.dist-info/METADATA
utlib-0.3.4.dist-info/WHEEL
utlib-0.3.4.dist-info/top_level.txt
utlib-0.3.4.dist-info/RECORD
