Metadata-Version: 2.4
Name: utlib
Version: 0.3.4
Summary: A utility library that contains useful functions, decorators and more
Author-email: Myroslav Repin <myroslavrepin@gmail.com>
License: MIT
Project-URL: Homepage, https://github.com/MyroslavRepin/utlib
Keywords: utilities,decorators,tools,functions,python,lib
Classifier: Programming Language :: Python :: 3
Classifier: License :: OSI Approved :: MIT License
Classifier: Operating System :: OS Independent
Requires-Python: >=3.7
License-File: LICENSE
Dynamic: license-file
